curveengine/__init__.py
curveengine/engine.py
curveengine/parsing/__init__.py
curveengine/parsing/checks.py
curveengine/parsing/enums.py
curveengine/parsing/others.py
curveengine/parsing/parsers.py
curveengine/parsing/ratehelpers.py
curveengine-1.1.7.dist-info/METADATA
curveengine-1.1.7.dist-info/WHEEL
curveengine-1.1.7.dist-info/top_level.txt
curveengine-1.1.7.dist-info/RECORD
