Metadata-Version: 2.1
Name: curveengine
Version: 1.1.7
Summary: A simple curve bootstraping tool based on ORE/QuantLib
Author-email: Jose Melo <jmelo@live.com>
Project-URL: Homepage, https://github.com/jmelo11/curveengine
Classifier: Programming Language :: Python :: 3
Classifier: License :: OSI Approved :: MIT License
Classifier: Operating System :: OS Independent
Requires-Python: >=3.10
